setup.py
zelas/Ellipse.py
zelas/Multispectral.py
zelas/RedundancyElimination.py
zelas/TheHeartOfTheMilitaryGod.py
zelas/__init__.py
zelas/dxf_dwg.py
zelas/ransac.py
zelas/setup.py
zelas/shield.py
zelas/voxel.py
zelas.egg-info/PKG-INFO
zelas.egg-info/SOURCES.txt
zelas.egg-info/dependency_links.txt
zelas.egg-info/top_level.txt