Metadata-Version: 2.1
Name: zelas
Version: 1.6.240819
Summary: Professor Liying Wang official point clouds algorithm library
Home-page: UNKNOWN
Author: Ze You, Huaxin Chen, Yimo Geng, Mengyao Gao
Author-email: youze1997@163.com
License: UNKNOWN
Keywords: python,point clouds
Platform: UNKNOWN
Classifier: Intended Audience :: Developers
Classifier: Programming Language :: Python :: 3.8
Classifier: Operating System :: Unix
Classifier: Operating System :: MacOS :: MacOS X
Classifier: Operating System :: Microsoft :: Windows
